all_math_ops/__init__.py
all_math_ops/__version__.py
all_math_ops/addition_module.py
all_math_ops/division_module.py
all_math_ops/multiplication_module.py
all_math_ops/subtraction_module.py
demo_math_ops-1.0.dist-info/LICENSE
demo_math_ops-1.0.dist-info/METADATA
demo_math_ops-1.0.dist-info/WHEEL
demo_math_ops-1.0.dist-info/top_level.txt
demo_math_ops-1.0.dist-info/RECORD
